<PAMDataset>
  <PAMRasterBand band="1">
    <Description>Band_1</Description>
    <Histograms>
      <HistItem>
        <HistMin>2.837961673736572</HistMin>
        <HistMax>40.23209381103516</HistMax>
        <BucketCount>256</BucketCount>
        <IncludeOutOfRange>1</IncludeOutOfRange>
        <Approximate>0</Approximate>
        <HistCounts>2|4|32|89|259|668|1594|3991|9484|21979|50209|121471|414104|1515754|3103649|4616872|5940844|7667817|10535612|13489046|16945404|20456168|24060671|28196351|32759852|37211733|41756088|46372854|50590022|53758412|56523041|57894426|57987620|56978309|54956642|52436499|49830139|46021491|43476693|40299916|36739290|33694601|30991656|28902104|25916184|23370018|21425674|19417984|17748590|16061987|14630030|13296917|12120303|11047888|10099330|9246555|8488259|7834029|7216131|6655441|6147137|5716865|5331341|4974674|4668675|4396424|4141242|3911324|3700979|3513897|3335636|3177669|3019622|2869277|2740217|2633689|2508707|2391298|2287045|2182922|2073380|1977426|1888820|1800444|1718964|1640418|1568197|1498476|1423845|1359279|1294808|1232833|1175896|1120352|1068700|1015091|964672|916041|872051|839474|788373|753675|707690|668244|636982|596055|576148|538631|512282|487554|461827|432742|410330|384052|373821|345506|313996|319343|344586|307976|421034|292828|397950|465791|366747|686464|407447|293423|317958|347744|473925|331718|320089|334755|345921|331238|383929|377611|385568|399045|473812|454483|508917|534859|554245|573409|623346|600003|625236|615375|611252|606419|584361|562223|534993|495482|463614|434861|404771|385402|362871|339245|321015|300552|282983|254324|211052|164455|130258|112480|98176|89348|69005|49514|39891|33291|34680|28185|26512|24629|24362|21642|20284|17294|17369|14959|15841|15036|12599|13577|12277|10594|10941|10774|10006|8987|8144|6546|9792|6674|7923|6594|6335|7018|5674|5314|6277|7015|6505|5660|4545|5167|4467|5687|4010|4044|2900|3933|3010|2736|2568|3760|2528|3428|2017|2149|2212|2308|1897|1352|2864|2200|4167|4024|1115|2028|2437|2635|2600|1195|579|761|593|1289|1375|1197|1786|1792|217|907|1667|2844|74|235|2282|1</HistCounts>
      </HistItem>
    </Histograms>
    <Metadata>
      <MDI key="STATISTICS_COUNT">1403706711.000000</MDI>
      <MDI key="STATISTICS_EXCLUDEDVALUES"></MDI>
      <MDI key="STATISTICS_MAXIMUM">40.232093811035</MDI>
      <MDI key="STATISTICS_MEAN">8.7205932164471</MDI>
      <MDI key="STATISTICS_MEDIAN">nan</MDI>
      <MDI key="STATISTICS_MINIMUM">2.8379616737366</MDI>
      <MDI key="STATISTICS_SKIPFACTORX">1</MDI>
      <MDI key="STATISTICS_SKIPFACTORY">1</MDI>
      <MDI key="STATISTICS_STDDEV">2.9399484092047</MDI>
    </Metadata>
  </PAMRasterBand>
</PAMDataset>
